castana/__init__.py
castana/_compat.py
castana/domain.py
castana/exceptions.py
castana/main.py
castana/runner.py
castana/utils.py
castana/adapters/__init__.py
castana/adapters/base.py
castana/adapters/django.py
castana/adapters/fastapi.py
castana/adapters/flask.py
castana/metrics/__init__.py
castana/metrics/prometheus.py
castana/observers/__init__.py
castana/observers/base.py
castana/probes/__init__.py
castana/probes/base.py
castana/probes/http.py
castana/probes/redis.py
castana/probes/sql.py
castana/probes/system.py
castana/py.typed
castana-1.0.0.dist-info/METADATA
castana-1.0.0.dist-info/WHEEL
castana-1.0.0.dist-info/licenses/LICENSE
castana-1.0.0.dist-info/RECORD
