Metadata-Version: 2.4
Name: castana
Version: 1.0.0
Summary: Fresh, organic health checks for Python.
Author-email: suaue <suaue@users.noreply.github.com>
License-Expression: MIT
License-File: LICENSE
Classifier: Framework :: AsyncIO
Classifier: Intended Audience :: Developers
Classifier: License :: OSI Approved :: MIT License
Classifier: Operating System :: OS Independent
Classifier: Programming Language :: Python :: 3
Classifier: Programming Language :: Python :: 3.9
Classifier: Programming Language :: Python :: 3.10
Classifier: Programming Language :: Python :: 3.11
Classifier: Programming Language :: Python :: 3.12
Classifier: Programming Language :: Python :: 3.13
Classifier: Topic :: System :: Monitoring
Requires-Python: >=3.9
Provides-Extra: all
Requires-Dist: asyncpg>=0.27.0; extra == 'all'
Requires-Dist: httpx>=0.24; extra == 'all'
Requires-Dist: prometheus-client>=0.17.0; extra == 'all'
Requires-Dist: psutil>=5.0; extra == 'all'
Requires-Dist: redis>=4.5.0; extra == 'all'
Provides-Extra: dev
Requires-Dist: asyncpg; extra == 'dev'
Requires-Dist: django; extra == 'dev'
Requires-Dist: fastapi; extra == 'dev'
Requires-Dist: flask; extra == 'dev'
Requires-Dist: httpx; extra == 'dev'
Requires-Dist: prometheus-client; extra == 'dev'
Requires-Dist: psycopg2-binary; extra == 'dev'
Requires-Dist: pytest; extra == 'dev'
Requires-Dist: pytest-asyncio; extra == 'dev'
Requires-Dist: redis; extra == 'dev'
Provides-Extra: http
Requires-Dist: httpx>=0.24; extra == 'http'
Provides-Extra: postgres
Requires-Dist: asyncpg>=0.27.0; extra == 'postgres'
Provides-Extra: prometheus
Requires-Dist: prometheus-client>=0.17.0; extra == 'prometheus'
Provides-Extra: redis
Requires-Dist: redis>=4.5.0; extra == 'redis'
Provides-Extra: system
Requires-Dist: psutil>=5.0; extra == 'system'
